{"title":"238 BrazzersExxtra Kristina Rose ZZ Lemonade Kristina Rose 02","uid":15955703,"size":314170950,"categoryP":"porn","categoryS":"movie_clips","magnet":"?xt=urn:btih:03ccc3d70c90fdac53a8618f98134d65862501c5&amp;dn=238+BrazzersExxtra+Kristina+Rose+ZZ+Lemonade+Kristina+Rose+02&amp;tr=udp%3A%2F%2Ftracker.leechers-paradise.org%3A6969&amp;tr=udp%3A%2F%2Fzer0day.ch%3A1337&amp;tr=udp%3A%2F%2Fopen.demonii.com%3A1337&amp;tr=udp%3A%2F%2Ftracker.coppersurfer.tk%3A6969&amp;tr=udp%3A%2F%2Fexodus.desync.com%3A6969","seeders":1,"leechers":0,"uploader":"RandalPaul","files":1,"time":1475616745,"description":"\n\n  Image Links \t:  http://imgbonk.com/image/5LRkR  \n\n  Image Links \t:  http://imgbonk.com/image/5LSb4  \n\n  Image Sheet \t:  http://imgshag.com/image/J3Hgh \n\n \t \t \t Get More Small Sized XXX Videos \n \n \t   https://thepiratebay.se/user/RandalPaul/506","torrent":{"xt":"urn:btih:03ccc3d70c90fdac53a8618f98134d65862501c5","amp;dn":"238+BrazzersExxtra+Kristina+Rose+ZZ+Lemonade+Kristina+Rose+02","amp;tr":["udp%3A%2F%2Ftracker.leechers-paradise.org%3A6969","udp%3A%2F%2Fzer0day.ch%3A1337","udp%3A%2F%2Fopen.demonii.com%3A1337","udp%3A%2F%2Ftracker.coppersurfer.tk%3A6969","udp%3A%2F%2Fexodus.desync.com%3A6969"],"infoHash":"03ccc3d70c90fdac53a8618f98134d65862501c5","infoHashBuffer":{"type":"Buffer","data":[3,204,195,215,12,144,253,172,83,168,97,143,152,19,77,101,134,37,1,197]},"announce":[],"urlList":[]}}