{"title":"Rizzoli.and.Isles.S04E04.Xvid-AJAXEN.avi","uid":8700919,"size":304942320,"categoryP":"video","categoryS":"tv_shows","magnet":"?xt=urn:btih:0af7e2ad7b4203adf10fe21d90d46d589221a2a1&amp;dn=Rizzoli.and.Isles.S04E04.Xvid-AJAXEN.avi&amp;tr=udp%3A%2F%2Ftracker.openbittorrent.com%3A80&amp;tr=udp%3A%2F%2Fopen.demonii.com%3A1337&amp;tr=udp%3A%2F%2Ftracker.coppersurfer.tk%3A6969&amp;tr=udp%3A%2F%2Fexodus.desync.com%3A6969","seeders":1,"leechers":2,"uploader":"ajaxen94","files":1,"time":1374066506,"description":"aspect ratio...624x352\nframe rate...25\nbit rate...450 up to 900\naudio mp3 stereo...128.. 48khz\ncodec...Xvid avi\nre-converted using WINX Video Converter\ni download the smallest files i can find and re-convert them to xvid avi for my own use as  i  can't play any other format on my player so i thought i would upload them for anyone else who might  be able to use them ,i dont have a very fast upload speed so please be patient\n","torrent":{"xt":"urn:btih:0af7e2ad7b4203adf10fe21d90d46d589221a2a1","amp;dn":"Rizzoli.and.Isles.S04E04.Xvid-AJAXEN.avi","amp;tr":["udp%3A%2F%2Ftracker.openbittorrent.com%3A80","udp%3A%2F%2Fopen.demonii.com%3A1337","udp%3A%2F%2Ftracker.coppersurfer.tk%3A6969","udp%3A%2F%2Fexodus.desync.com%3A6969"],"infoHash":"0af7e2ad7b4203adf10fe21d90d46d589221a2a1","infoHashBuffer":{"type":"Buffer","data":[10,247,226,173,123,66,3,173,241,15,226,29,144,212,109,88,146,33,162,161]},"announce":[],"urlList":[]}}