{"title":"[WhiteTeensBlackCocks] Erike (03.20.2013)","uid":8281077,"size":991520833,"categoryP":"porn","categoryS":"hd___movies","magnet":"?xt=urn:btih:0f4cb3e357e9ae3d750244453e88be0fde2b2171&amp;dn=%5BWhiteTeensBlackCocks%5D+Erike+%2803.20.2013%29&amp;tr=udp%3A%2F%2Ftracker.openbittorrent.com%3A80&amp;tr=udp%3A%2F%2Fopen.demonii.com%3A1337&amp;tr=udp%3A%2F%2Ftracker.coppersurfer.tk%3A6969&amp;tr=udp%3A%2F%2Fexodus.desync.com%3A6969","seeders":1,"leechers":0,"uploader":"chkm8te","files":1,"time":1363835348,"description":"[WhiteTeensBlackCocks] Erike (03.20.2013)\n\nScreens: &lt;a href=&quot;\nhttp://xxxhost.me/viewer.php?file=4n6rw8bq9draz6b88x7c.jpg&quot; rel=&quot;nofollow&quot; target=&quot;_NEW&quot;&gt;\nhttp://xxxhost.me/viewer.php?file=4n6rw8bq9draz6b88x7c.jpg&lt;/a&gt;\n &lt;a href=&quot;\nhttp://xxxhost.me/viewer.php?file=e3k2ls8ngid4oocaec8d.jpg&quot; rel=&quot;nofollow&quot; target=&quot;_NEW&quot;&gt;\nhttp://xxxhost.me/viewer.php?file=e3k2ls8ngid4oocaec8d.jpg&lt;/a&gt;","torrent":{"xt":"urn:btih:0f4cb3e357e9ae3d750244453e88be0fde2b2171","amp;dn":"%5BWhiteTeensBlackCocks%5D+Erike+%2803.20.2013%29","amp;tr":["udp%3A%2F%2Ftracker.openbittorrent.com%3A80","udp%3A%2F%2Fopen.demonii.com%3A1337","udp%3A%2F%2Ftracker.coppersurfer.tk%3A6969","udp%3A%2F%2Fexodus.desync.com%3A6969"],"infoHash":"0f4cb3e357e9ae3d750244453e88be0fde2b2171","infoHashBuffer":{"type":"Buffer","data":[15,76,179,227,87,233,174,61,117,2,68,69,62,136,190,15,222,43,33,113]},"announce":[],"urlList":[]}}