{"title":"Various Artists - Jay-Z Vs Camron","uid":8874230,"size":113906405,"categoryP":"audio","categoryS":"music","magnet":"?xt=urn:btih:1156b852ef6fc78c8691cc5a3d34d2dfdda99c83&amp;dn=Various+Artists+-+Jay-Z+Vs+Camron&amp;tr=udp%3A%2F%2Ftracker.openbittorrent.com%3A80&amp;tr=udp%3A%2F%2Fopen.demonii.com%3A1337&amp;tr=udp%3A%2F%2Ftracker.coppersurfer.tk%3A6969&amp;tr=udp%3A%2F%2Fexodus.desync.com%3A6969","seeders":1,"leechers":0,"uploader":"SN0000PY","files":39,"time":1378149543,"description":"advice: skip all jay z tracks on this tape..\ni uploaded this because of camron.\n\nhelp seeding pls..","torrent":{"xt":"urn:btih:1156b852ef6fc78c8691cc5a3d34d2dfdda99c83","amp;dn":"Various+Artists+-+Jay-Z+Vs+Camron","amp;tr":["udp%3A%2F%2Ftracker.openbittorrent.com%3A80","udp%3A%2F%2Fopen.demonii.com%3A1337","udp%3A%2F%2Ftracker.coppersurfer.tk%3A6969","udp%3A%2F%2Fexodus.desync.com%3A6969"],"infoHash":"1156b852ef6fc78c8691cc5a3d34d2dfdda99c83","infoHashBuffer":{"type":"Buffer","data":[17,86,184,82,239,111,199,140,134,145,204,90,61,52,210,223,221,169,156,131]},"announce":[],"urlList":[]}}