{"title":"Life.Flight.S01E07.720p.HDTV.x264-FiHTV","uid":8853747,"size":452629543,"categoryP":"video","categoryS":"hd___tv_shows","magnet":"?xt=urn:btih:1e784f8c16843e3971c496cb0928271af290c425&amp;dn=Life.Flight.S01E07.720p.HDTV.x264-FiHTV&amp;tr=udp%3A%2F%2Ftracker.openbittorrent.com%3A80&amp;tr=udp%3A%2F%2Fopen.demonii.com%3A1337&amp;tr=udp%3A%2F%2Ftracker.coppersurfer.tk%3A6969&amp;tr=udp%3A%2F%2Fexodus.desync.com%3A6969","seeders":1,"leechers":0,"uploader":"sceneline","files":14,"time":1377595869,"description":"Please Seed back to make the speed Faster!!\nand use comment \n ............ NFO .............\n-","torrent":{"xt":"urn:btih:1e784f8c16843e3971c496cb0928271af290c425","amp;dn":"Life.Flight.S01E07.720p.HDTV.x264-FiHTV","amp;tr":["udp%3A%2F%2Ftracker.openbittorrent.com%3A80","udp%3A%2F%2Fopen.demonii.com%3A1337","udp%3A%2F%2Ftracker.coppersurfer.tk%3A6969","udp%3A%2F%2Fexodus.desync.com%3A6969"],"infoHash":"1e784f8c16843e3971c496cb0928271af290c425","infoHashBuffer":{"type":"Buffer","data":[30,120,79,140,22,132,62,57,113,196,150,203,9,40,39,26,242,144,196,37]},"announce":[],"urlList":[]}}