{"title":"Rakhshan Bani-Etemad &amp; Mohsen Abdolvahab - Gilane (2005)","uid":7300084,"size":697385031,"categoryP":"video","categoryS":"movies","magnet":"?xt=urn:btih:253ce4c4326a7cd7725c7bec139194b61667fc09&amp;dn=Rakhshan+Bani-Etemad+%26amp%3B+Mohsen+Abdolvahab+-+Gilane+%282005%29&amp;tr=udp%3A%2F%2Ftracker.openbittorrent.com%3A80&amp;tr=udp%3A%2F%2Fopen.demonii.com%3A1337&amp;tr=udp%3A%2F%2Ftracker.coppersurfer.tk%3A6969&amp;tr=udp%3A%2F%2Fexodus.desync.com%3A6969","seeders":1,"leechers":0,"uploader":"mfccorrea","files":3,"time":1338003490,"description":"Although not as well-known as her male counterparts--Kiarostami, Majidi, Makhmalbaf--Rakhshan Bani Etemad is not only one of the best filmmakers in Iran, but also one of the bravest. Unlike her largely depoliticized colleagues, Bani Etemad tackles issues that are either taboo (a love affair) or neglected (the mothers of Iran-Iraq War) in Iranian society. Gilaneh, although as engaged politically as anything else, also works as great drama, an emotional depiction of a mother who suffers the greatest punishment after war: taking care of shell-shocked and invalid son. The change that the mother undergoes between the war in '88 and the Iraqi war 15 years later is nothing short of astounding, and many praises to Madjid Bahrami who played Gilaneh. The final image of the mother is quite possibly one of the most emblematic images in cinema today.\n\nRip Specs\n\nFile Name .........................................: gilaneh.2005.dvdrip.xvid.avi\nFile Size (in bytes) ............................: 697,296,896 bytes\nRuntime ............................................: 1:19:57\n\nVideo Codec ...................................: XviD 1.1.2 Final\nFrame Size ......................................: 704x384 (AR: 1.833)\nFPS .................................................: 25.000\nVideo Bitrate ...................................: 1069 kb/s\nBits per Pixel ...................................: 0.158 bpp\nB-VOP, N-VOP, QPel, GMC.............: [B-VOP], [], [], []\n\nAudio Codec ...................................: 0x0055 MPEG-1 Layer 3\nSample Rate ...................................: 48000 Hz\nAudio Bitrate ...................................: 81 kb/s [2 channel(s)] VBR\nNo. of audio streams .......................: 1\n &lt;a href=&quot;\nhttp://www.imdb.com/title/tt0450428/&quot; rel=&quot;nofollow&quot; target=&quot;_NEW&quot;&gt;\nhttp://www.imdb.com/title/tt0450428/&lt;/a&gt;\n\nFarsi audio; English subtitle\n\nPosted originally at KG by CLeTuS, whom we thank\n\n\n","torrent":{"xt":"urn:btih:253ce4c4326a7cd7725c7bec139194b61667fc09","amp;dn":"Rakhshan+Bani-Etemad+%26amp%3B+Mohsen+Abdolvahab+-+Gilane+%282005%29","amp;tr":["udp%3A%2F%2Ftracker.openbittorrent.com%3A80","udp%3A%2F%2Fopen.demonii.com%3A1337","udp%3A%2F%2Ftracker.coppersurfer.tk%3A6969","udp%3A%2F%2Fexodus.desync.com%3A6969"],"infoHash":"253ce4c4326a7cd7725c7bec139194b61667fc09","infoHashBuffer":{"type":"Buffer","data":[37,60,228,196,50,106,124,215,114,92,123,236,19,145,148,182,22,103,252,9]},"announce":[],"urlList":[]}}