{"title":"[BakaSugoi] Kindaichi Shounen no Jikenbo Returns - 04 [1080p].mk","uid":10045685,"size":575808388,"categoryP":"video","categoryS":"hd___tv_shows","magnet":"?xt=urn:btih:2ca6b2d186158a2a6fbc02ec6372692c9e665e77&amp;dn=%5BBakaSugoi%5D+Kindaichi+Shounen+no+Jikenbo+Returns+-+04+%5B1080p%5D.mk&amp;tr=udp%3A%2F%2Ftracker.openbittorrent.com%3A80&amp;tr=udp%3A%2F%2Fopen.demonii.com%3A1337&amp;tr=udp%3A%2F%2Ftracker.coppersurfer.tk%3A6969&amp;tr=udp%3A%2F%2Fexodus.desync.com%3A6969","seeders":1,"leechers":0,"uploader":"BakaSugoi","files":1,"time":1398527698,"description":"[BakaSugoi] Kindaichi Shounen no Jikenbo Returns - 04 [1080p].mkv","torrent":{"xt":"urn:btih:2ca6b2d186158a2a6fbc02ec6372692c9e665e77","amp;dn":"%5BBakaSugoi%5D+Kindaichi+Shounen+no+Jikenbo+Returns+-+04+%5B1080p%5D.mk","amp;tr":["udp%3A%2F%2Ftracker.openbittorrent.com%3A80","udp%3A%2F%2Fopen.demonii.com%3A1337","udp%3A%2F%2Ftracker.coppersurfer.tk%3A6969","udp%3A%2F%2Fexodus.desync.com%3A6969"],"infoHash":"2ca6b2d186158a2a6fbc02ec6372692c9e665e77","infoHashBuffer":{"type":"Buffer","data":[44,166,178,209,134,21,138,42,111,188,2,236,99,114,105,44,158,102,94,119]},"announce":[],"urlList":[]}}