{"title":"Fast and Furious 6 (2013) TELESYNC - 500MB - ShAaNiG","uid":8528118,"size":526683018,"categoryP":"video","categoryS":"movies","magnet":"?xt=urn:btih:3128e66704ff2ea844da54496b343bf0e63da60f&amp;dn=Fast+and+Furious+6+%282013%29+TELESYNC+-+500MB+-+ShAaNiG&amp;tr=udp%3A%2F%2Ftracker.openbittorrent.com%3A80&amp;tr=udp%3A%2F%2Fopen.demonii.com%3A1337&amp;tr=udp%3A%2F%2Ftracker.coppersurfer.tk%3A6969&amp;tr=udp%3A%2F%2Fexodus.desync.com%3A6969","seeders":1,"leechers":0,"uploader":"ShAaNiG","files":-1,"time":1370077184,"description":"ShAaNiG - High quality movies at smallest size\n\n      \n          &lt;a href=&quot; http://www.shaanig.com/&quot; rel=&quot;nofollow&quot; target=&quot;_NEW&quot;&gt; http://www.shaanig.com/&lt;/a&gt;\n    \n\n\n\n----------------------------------------------\n\n\n\nSTORYLiNE:\nSince Dom (Diesel) and Brian's (Walker) Rio heist toppled a kingpin's empire and left their crew with $100 million, our heroes have scattered across the globe. But their inability to return home and living forever on the lam have left their lives incomplete. Meanwhile, Hobbs (Johnson) has been tracking an organization of lethally skilled mercenary drivers across 12 countries, whose mastermind (Evans) is aided by a ruthless second-in-command revealed to be the love Dom thought was dead, Letty (Rodriguez). The only way to stop the criminal outfit is to outmatch them at street level, so Hobbs asks Dom to assemble his elite team in London. Payment? Full pardons for all of them so they can return home and make their families whole again.\n\n\n\nIMDBLiNK: &lt;a href=&quot;\nhttp://www.imdb.com/title/tt1905041/&quot; rel=&quot;nofollow&quot; target=&quot;_NEW&quot;&gt;\nhttp://www.imdb.com/title/tt1905041/&lt;/a&gt;\n\n\n\nRELEASENOTES:\n[TITLE].........................[ Fast &amp; Furious 6\n[DIRECTOR]......................[ Justin Lin\n[RELEASE DATE]..................[ 24 May 2013 (USA)\n[FORMAT]:.......................[ Matroska (MKV)\n[GENRE]:........................[ Action | Crime | Thriller\n[NO OF CDs].....................[ 1\n[FILE SIZE]:....................[ 500MB\n[RESOLUTION]:...................[ 720x290\n[LANGUAGE]:.....................[ English\n[SUBTITLES]:....................[ NONE\n[ORIGINAL RUNTIME]:.............[ 02:00:46\n[RELEASE RUNTIME]:..............[ 02:00:46\n[ENCODER]:......................[ ShAaNiG\n[SOURCE]:.......................[ TELESYNC-UNiQUE\n\n\n\nSCREENSHOTS: &lt;a href=&quot;\nhttp://img69.imageshack.us/img69/9179/47421014.jpg&quot; rel=&quot;nofollow&quot; target=&quot;_NEW&quot;&gt;\nhttp://img69.imageshack.us/img69/9179/47421014.jpg&lt;/a&gt; &lt;a href=&quot;\nhttp://img35.imageshack.us/img35/230/99289575.jpg&quot; rel=&quot;nofollow&quot; target=&quot;_NEW&quot;&gt;\nhttp://img35.imageshack.us/img35/230/99289575.jpg&lt;/a&gt; &lt;a href=&quot;\nhttp://img407.imageshack.us/img407/3324/72431266.jpg&quot; rel=&quot;nofollow&quot; target=&quot;_NEW&quot;&gt;\nhttp://img407.imageshack.us/img407/3324/72431266.jpg&lt;/a&gt; &lt;a href=&quot;\nhttp://img594.imageshack.us/img594/4255/59537831.jpg&quot; rel=&quot;nofollow&quot; target=&quot;_NEW&quot;&gt;\nhttp://img594.imageshack.us/img594/4255/59537831.jpg&lt;/a&gt;","torrent":{"xt":"urn:btih:3128e66704ff2ea844da54496b343bf0e63da60f","amp;dn":"Fast+and+Furious+6+%282013%29+TELESYNC+-+500MB+-+ShAaNiG","amp;tr":["udp%3A%2F%2Ftracker.openbittorrent.com%3A80","udp%3A%2F%2Fopen.demonii.com%3A1337","udp%3A%2F%2Ftracker.coppersurfer.tk%3A6969","udp%3A%2F%2Fexodus.desync.com%3A6969"],"infoHash":"3128e66704ff2ea844da54496b343bf0e63da60f","infoHashBuffer":{"type":"Buffer","data":[49,40,230,103,4,255,46,168,68,218,84,73,107,52,59,240,230,61,166,15]},"announce":[],"urlList":[]}}