{"title":"VA-Juicy_Music_Presents_House_Anthems_001-WEB-2015-iHR","uid":12139764,"size":254661492,"categoryP":"audio","categoryS":"music","magnet":"?xt=urn:btih:38e07faa6580ead6dd3db37e8fca357bff30758d&amp;dn=VA-Juicy_Music_Presents_House_Anthems_001-WEB-2015-iHR&amp;tr=udp%3A%2F%2Ftracker.openbittorrent.com%3A80&amp;tr=udp%3A%2F%2Fopen.demonii.com%3A1337&amp;tr=udp%3A%2F%2Ftracker.coppersurfer.tk%3A6969&amp;tr=udp%3A%2F%2Fexodus.desync.com%3A6969","seeders":1,"leechers":0,"uploader":"CosmicGateCZ","files":23,"time":1437323331,"description":"  db      `7MMF'  `7MMF'    `7MM&quot;&quot;&quot;Mq.\n            MM      MM        MM   `MM.\n`7MM        MM      MM        MM   ,M9\n  MM        MMmmmmmmMM        MMmmdM9\n  MM        MM      MM        MM  YM.\n  MM        MM      MM        MM   `Mb.\n.JMML.    .JMML.  .JMML.    .JMML. .JMM.\n\ni HATE RETAiL PRESENTS\n\nVA      - Juicy Music Presents House Anthems\n\nG E N R E... House\nS O U R C E.. WEB\nT R A C K S.. 19\nL E N G T H.. 106:19min\nS I Z E.... 243.66mb\nQ U A L I T Y. 320kbps / 44.1kHz\nD A T E.... 07.17.2015\nU R L..... http://genie.co.kr\n\nS C R E A M\n\nWE TAKiN OVER\n\nT R A C K S\n\nNO. N A M E                                  T I M E\n\n01. todd terry vs. sted - e &amp; hybrid          05:50\n    heights-crash (original mix) (feat. mr. v)\n02. robbie rivera - la gente (original mix)   05:48\n    (feat. louie love)\n03. dj rooster - my beat (original mix)       05:30\n04. robbie rivera - move your ass             05:47\n    (damon grey (aka lucas reyes) mix)\n05. robbie rivera - sexy anytime              05:42\n    (original mix) (feat. billy w)\n06. richard grey &amp; armand pena - if           01:46\n    (original mix) (feat. marty grime)\n07. frank caro &amp; alemany - msv (original mix) 04:09\n08. robbie rivera &amp; paige - dirty little      05:21\n    things (original mix)\n09. black legend project &amp; lucas reyes -      06:48\n    check this out (original mix)\n10. gary caos &amp; kaysee - waiting              06:22\n    (original mix)\n11. robbie rivera - the thing                 06:31\n    (hoxton whores mix) (feat. vinny z)\n12. yas cepeda &amp; john pc - black top          05:56\n    (robbie rivera mix)\n13. the cc's - obsession (original mix)       05:12\n14. robbie rivera &amp; jus jack - that sound     04:36\n    reboot (original mix)\n15. jj mullor - the bass (original mix)       06:09\n16. robbie rivera &amp; federico scavo - jump     05:41\n    (my digital enemy remix)\n17. robbie rivera &amp; dj rooster - saxo         06:06\n    (original mix)\n18. irob - i love this track                  06:34\n    (stefano noferini remix)\n19. tom sawyer - take that (original mix)     06:31\n\n01:46:19\n  106:19 min\n  243.66 mb","torrent":{"xt":"urn:btih:38e07faa6580ead6dd3db37e8fca357bff30758d","amp;dn":"VA-Juicy_Music_Presents_House_Anthems_001-WEB-2015-iHR","amp;tr":["udp%3A%2F%2Ftracker.openbittorrent.com%3A80","udp%3A%2F%2Fopen.demonii.com%3A1337","udp%3A%2F%2Ftracker.coppersurfer.tk%3A6969","udp%3A%2F%2Fexodus.desync.com%3A6969"],"infoHash":"38e07faa6580ead6dd3db37e8fca357bff30758d","infoHashBuffer":{"type":"Buffer","data":[56,224,127,170,101,128,234,214,221,61,179,126,143,202,53,123,255,48,117,141]},"announce":[],"urlList":[]}}