{"title":"Bram Stoker - Midnight Tales","uid":7201528,"size":35048279,"categoryP":"audio","categoryS":"audio_books","magnet":"?xt=urn:btih:42bb1f0bb709626ddd2cc0fb794cb7615db1f4a5&amp;dn=Bram+Stoker+-+Midnight+Tales&amp;tr=udp%3A%2F%2Ftracker.openbittorrent.com%3A80&amp;tr=udp%3A%2F%2Fopen.demonii.com%3A1337&amp;tr=udp%3A%2F%2Ftracker.coppersurfer.tk%3A6969&amp;tr=udp%3A%2F%2Fexodus.desync.com%3A6969","seeders":1,"leechers":0,"uploader":"fakeplastictrousers2","files":7,"time":1334953992,"description":"Midnight Tales\n\nFrom BBC Radio 4 Extra. Written by Bram Stoker; Read by Dyfed Thomas.\n\nThe Secret of Growing Gold\n\nFair hair becomes an unusual tool of marital revenge.\n\nThe Coming of Abel Behenna\n\nTwo rivals in love make a pact. Will it end in betrayal?\n\nThe Dream in the Dead House\n\nAn Englishman in Munichis rescued by a most unexpected source.\n\nA Dream of Red Hands\n\nJacob Settle hides a dark past. What does his dream mean?\n\nThe Squaw\n\nAn arrogant American earns himself a horrific retribution.\n\n\nPlease note: These stories are ABRIDGED.","torrent":{"xt":"urn:btih:42bb1f0bb709626ddd2cc0fb794cb7615db1f4a5","amp;dn":"Bram+Stoker+-+Midnight+Tales","amp;tr":["udp%3A%2F%2Ftracker.openbittorrent.com%3A80","udp%3A%2F%2Fopen.demonii.com%3A1337","udp%3A%2F%2Ftracker.coppersurfer.tk%3A6969","udp%3A%2F%2Fexodus.desync.com%3A6969"],"infoHash":"42bb1f0bb709626ddd2cc0fb794cb7615db1f4a5","infoHashBuffer":{"type":"Buffer","data":[66,187,31,11,183,9,98,109,221,44,192,251,121,76,183,97,93,177,244,165]},"announce":[],"urlList":[]}}