{"title":"Brand xxx - Hong Kong Cooter 4 DVDRip.mp4","uid":11794932,"size":1338820908,"categoryP":"porn","categoryS":"movies","magnet":"?xt=urn:btih:480dea11357dc553195d19207d5a4a317800bf25&amp;dn=Brand+xxx+-+Hong+Kong+Cooter+4+DVDRip.mp4&amp;tr=udp%3A%2F%2Ftracker.openbittorrent.com%3A80&amp;tr=udp%3A%2F%2Fopen.demonii.com%3A1337&amp;tr=udp%3A%2F%2Ftracker.coppersurfer.tk%3A6969&amp;tr=udp%3A%2F%2Fexodus.desync.com%3A6969","seeders":1,"leechers":1,"uploader":"PornKing","files":1,"time":1428101143,"description":"Brand xxx - Hong Kong Cooter 4 DVDRip.mp4\n\n2013, Asian, Compilation, All Sex, Anal, DP, Facial, DVDRip, XXX, Adult\n\n1.25 GB\n\nScreens\n &lt;a href=&quot;\nhttp://imgcentral.com/viewer.php?file=90525761974478072341.jpg&quot; rel=&quot;nofollow&quot; target=&quot;_NEW&quot;&gt;\nhttp://imgcentral.com/viewer.php?file=90525761974478072341.jpg&lt;/a&gt;\n &lt;a href=&quot;\nhttp://imgcentral.com/viewer.php?file=80196743308339375938.jpg&quot; rel=&quot;nofollow&quot; target=&quot;_NEW&quot;&gt;\nhttp://imgcentral.com/viewer.php?file=80196743308339375938.jpg&lt;/a&gt;\n &lt;a href=&quot;\nhttp://imgcentral.com/viewer.php?file=12982044095112470611.jpg&quot; rel=&quot;nofollow&quot; target=&quot;_NEW&quot;&gt;\nhttp://imgcentral.com/viewer.php?file=12982044095112470611.jpg&lt;/a&gt;","torrent":{"xt":"urn:btih:480dea11357dc553195d19207d5a4a317800bf25","amp;dn":"Brand+xxx+-+Hong+Kong+Cooter+4+DVDRip.mp4","amp;tr":["udp%3A%2F%2Ftracker.openbittorrent.com%3A80","udp%3A%2F%2Fopen.demonii.com%3A1337","udp%3A%2F%2Ftracker.coppersurfer.tk%3A6969","udp%3A%2F%2Fexodus.desync.com%3A6969"],"infoHash":"480dea11357dc553195d19207d5a4a317800bf25","infoHashBuffer":{"type":"Buffer","data":[72,13,234,17,53,125,197,83,25,93,25,32,125,90,74,49,120,0,191,37]},"announce":[],"urlList":[]}}