{"title":"Sleepy Hollow[HDRip][Castellano].avi","uid":6047227,"size":1997283328,"categoryP":"video","categoryS":"movies","magnet":"?xt=urn:btih:4ae3c7f2b9b8966ef00096f0da37773ffd8aa9df&amp;dn=Sleepy+Hollow%5BHDRip%5D%5BCastellano%5D.avi&amp;tr=udp%3A%2F%2Ftracker.openbittorrent.com%3A80&amp;tr=udp%3A%2F%2Fopen.demonii.com%3A1337&amp;tr=udp%3A%2F%2Ftracker.coppersurfer.tk%3A6969&amp;tr=udp%3A%2F%2Fexodus.desync.com%3A6969","seeders":1,"leechers":0,"uploader":"erato99","files":1,"time":1292603179,"description":"Titulo Original: Sleepy Hollow \nCalidad de video: HD Rip\nPeso: 1850 mb\nIdioma del audio: EspaÃƒÂ±ol \n\nDurante la Guerra de SecesiÃƒÂ³n Americana, un policÃƒÂ­a de Nueva York que utiliza avanzados mÃƒÂ©todos de investigaciÃƒÂ³n es enviado al pueblo de Sleepy Hollow para descubrir quÃƒÂ© hay de verdad en la leyenda de un jinete sin cabeza que aterroriza a los habitantes del lugar. Una vez allÃƒÂ­ adopta la identidad de un profesor de escuela y se enamora de Katrina, que mantiene relaciones con uno de los hombres mÃƒÂ¡s conocidos del pueblo. Realidad y ficciÃƒÂ³n se darÃƒÂ¡n la mano en el momento menos pensado.\n\nNos Vemos por TorrentSpain","torrent":{"xt":"urn:btih:4ae3c7f2b9b8966ef00096f0da37773ffd8aa9df","amp;dn":"Sleepy+Hollow%5BHDRip%5D%5BCastellano%5D.avi","amp;tr":["udp%3A%2F%2Ftracker.openbittorrent.com%3A80","udp%3A%2F%2Fopen.demonii.com%3A1337","udp%3A%2F%2Ftracker.coppersurfer.tk%3A6969","udp%3A%2F%2Fexodus.desync.com%3A6969"],"infoHash":"4ae3c7f2b9b8966ef00096f0da37773ffd8aa9df","infoHashBuffer":{"type":"Buffer","data":[74,227,199,242,185,184,150,110,240,0,150,240,218,55,119,63,253,138,169,223]},"announce":[],"urlList":[]}}