{"title":"The Princess And The Frog TS READNFO XVID - IMAGiNE","uid":5282807,"size":755180715,"categoryP":"video","categoryS":"movies","magnet":"?xt=urn:btih:589d691f3d94b5b3687ff0f3294965180501c7ae&amp;dn=The+Princess+And+The+Frog+TS+READNFO+XVID+-+IMAGiNE&amp;tr=udp%3A%2F%2Ftracker.openbittorrent.com%3A80&amp;tr=udp%3A%2F%2Fopen.demonii.com%3A1337&amp;tr=udp%3A%2F%2Ftracker.coppersurfer.tk%3A6969&amp;tr=udp%3A%2F%2Fexodus.desync.com%3A6969","seeders":1,"leechers":0,"uploader":".BONE.","files":4,"time":1263608600,"description":"Video Codec.......: XVID\nAudio Codec.......:MP3\nAudio Bitrate.....:128\nRuntime.......:1h 34mn\nSubtitles.........:NIL\nLanguage..........:ENGLISH\nResolution...... 640 x 352\n\nPlot: A modern day retelling of the classic story The Frog Prince. The Princess and the Frog finds the lives of arrogant, carefree Prince Naveen and hardworking waitress Tiana crossing paths. Prince Naveen is transformed into a frog by a conniving voodoo magician and Tiana, following suit, upon kissing the amphibian royalty. With the help of a trumpet-playing alligator, a Cajun firefly, and an old blind lady who lives in a boat in a tree, Naveen and Tiana must race to break the spell and fulfill their dreams.","torrent":{"xt":"urn:btih:589d691f3d94b5b3687ff0f3294965180501c7ae","amp;dn":"The+Princess+And+The+Frog+TS+READNFO+XVID+-+IMAGiNE","amp;tr":["udp%3A%2F%2Ftracker.openbittorrent.com%3A80","udp%3A%2F%2Fopen.demonii.com%3A1337","udp%3A%2F%2Ftracker.coppersurfer.tk%3A6969","udp%3A%2F%2Fexodus.desync.com%3A6969"],"infoHash":"589d691f3d94b5b3687ff0f3294965180501c7ae","infoHashBuffer":{"type":"Buffer","data":[88,157,105,31,61,148,181,179,104,127,240,243,41,73,101,24,5,1,199,174]},"announce":[],"urlList":[]}}