{"title":"The.Devils.Hand.2014.WEB-DL.XviD.MP3-RARBG","uid":11171317,"size":889053484,"categoryP":"video","categoryS":"movies","magnet":"?xt=urn:btih:5f936395571c3fec97b253da9242ac8f989b404e&amp;dn=The.Devils.Hand.2014.WEB-DL.XviD.MP3-RARBG&amp;tr=udp%3A%2F%2Ftracker.openbittorrent.com%3A80&amp;tr=udp%3A%2F%2Fopen.demonii.com%3A1337&amp;tr=udp%3A%2F%2Ftracker.coppersurfer.tk%3A6969&amp;tr=udp%3A%2F%2Fexodus.desync.com%3A6969","seeders":1,"leechers":0,"uploader":"Drarbg","files":4,"time":1412714210,"description":" &lt;a href=&quot;https://rarbg.com&quot; rel=&quot;nofollow&quot; target=&quot;_NEW&quot;&gt;https://rarbg.com&lt;/a&gt;\n\nThe.Devils.Hand.2014.WEB-DL.XviD.MP3-RARBG\n\nAuto IMDB: &lt;a href=&quot;\nhttp://www.imdb.com/title/tt2290739/&quot; rel=&quot;nofollow&quot; target=&quot;_NEW&quot;&gt;\nhttp://www.imdb.com/title/tt2290739/&lt;/a&gt;\n\n-----------------------------------------\nScreens : &lt;a href=&quot;\nhttp://imgcrl.org/v/36631245130502760874/&quot; rel=&quot;nofollow&quot; target=&quot;_NEW&quot;&gt;\nhttp://imgcrl.org/v/36631245130502760874/&lt;/a&gt; &lt;a href=&quot;\nhttp://imgcrl.org/v/37096534048614589256/&quot; rel=&quot;nofollow&quot; target=&quot;_NEW&quot;&gt;\nhttp://imgcrl.org/v/37096534048614589256/&lt;/a&gt; &lt;a href=&quot;\nhttp://imgcrl.org/v/48206185535371085878/&quot; rel=&quot;nofollow&quot; target=&quot;_NEW&quot;&gt;\nhttp://imgcrl.org/v/48206185535371085878/&lt;/a&gt; &lt;a href=&quot;\nhttp://imgcrl.org/v/01865955091415194618/&quot; rel=&quot;nofollow&quot; target=&quot;_NEW&quot;&gt;\nhttp://imgcrl.org/v/01865955091415194618/&lt;/a&gt; &lt;a href=&quot;\nhttp://imgcrl.org/v/00993601174213718998/&quot; rel=&quot;nofollow&quot; target=&quot;_NEW&quot;&gt;\nhttp://imgcrl.org/v/00993601174213718998/&lt;/a&gt; &lt;a href=&quot;\nhttp://imgcrl.org/v/73475463833280766931/&quot; rel=&quot;nofollow&quot; target=&quot;_NEW&quot;&gt;\nhttp://imgcrl.org/v/73475463833280766931/&lt;/a&gt; &lt;a href=&quot;\nhttp://imgcrl.org/v/57269967103761863547/&quot; rel=&quot;nofollow&quot; target=&quot;_NEW&quot;&gt;\nhttp://imgcrl.org/v/57269967103761863547/&lt;/a&gt; &lt;a href=&quot;\nhttp://imgcrl.org/v/95079067055016663530/&quot; rel=&quot;nofollow&quot; target=&quot;_NEW&quot;&gt;\nhttp://imgcrl.org/v/95079067055016663530/&lt;/a&gt; &lt;a href=&quot;\nhttp://imgcrl.org/v/97601530932786324172/&quot; rel=&quot;nofollow&quot; target=&quot;_NEW&quot;&gt;\nhttp://imgcrl.org/v/97601530932786324172/&lt;/a&gt; &lt;a href=&quot;\nhttp://imgcrl.org/v/19889748980491355564/&quot; rel=&quot;nofollow&quot; target=&quot;_NEW&quot;&gt;\nhttp://imgcrl.org/v/19889748980491355564/&lt;/a&gt; &lt;a href=&quot;\nhttp://imgcrl.org/v/05781718090032097040/&quot; rel=&quot;nofollow&quot; target=&quot;_NEW&quot;&gt;\nhttp://imgcrl.org/v/05781718090032097040/&lt;/a&gt; &lt;a href=&quot;\nhttp://imgcrl.org/v/11555769284207812539/&quot; rel=&quot;nofollow&quot; target=&quot;_NEW&quot;&gt;\nhttp://imgcrl.org/v/11555769284207812539/&lt;/a&gt;\n\n-----------------------------------------\nAuto Media Info :\nVideo Format........: MPEG-4 Visual\nCodec ID............: XVID\nCodec ID/Hint.......: XviD\nLength..............: 1h25mn\nVideo...............: 720x304 ( 24.000fps )\nBitrate.............: 1180Kbps\nAudio Format........: MPEG Audio\nCodec ID............: 55\nCodec ID/Hint.......: MP3\nBit rate mode.......: Constant\nBitrate.............: 192Kbps\nChannel(s)..........: 2 channels\n\n","torrent":{"xt":"urn:btih:5f936395571c3fec97b253da9242ac8f989b404e","amp;dn":"The.Devils.Hand.2014.WEB-DL.XviD.MP3-RARBG","amp;tr":["udp%3A%2F%2Ftracker.openbittorrent.com%3A80","udp%3A%2F%2Fopen.demonii.com%3A1337","udp%3A%2F%2Ftracker.coppersurfer.tk%3A6969","udp%3A%2F%2Fexodus.desync.com%3A6969"],"infoHash":"5f936395571c3fec97b253da9242ac8f989b404e","infoHashBuffer":{"type":"Buffer","data":[95,147,99,149,87,28,63,236,151,178,83,218,146,66,172,143,152,155,64,78]},"announce":[],"urlList":[]}}