{"title":"{PornDoePremium - TheWhiteBoxxx} Sapphira - Beautiful Brunette","uid":14557943,"size":225804278,"categoryP":"porn","categoryS":"other","magnet":"?xt=urn:btih:676d4c34381773cad5adc45e6f1d6da987ed35e3&amp;dn=+%7BPornDoePremium+-+TheWhiteBoxxx%7D+Sapphira+-+Beautiful+Brunette+&amp;tr=udp%3A%2F%2Ftracker.leechers-paradise.org%3A6969&amp;tr=udp%3A%2F%2Fzer0day.ch%3A1337&amp;tr=udp%3A%2F%2Fopen.demonii.com%3A1337&amp;tr=udp%3A%2F%2Ftracker.coppersurfer.tk%3A6969&amp;tr=udp%3A%2F%2Fexodus.desync.com%3A6969","seeders":1,"leechers":0,"uploader":"porn4u","files":1,"time":1462706916,"description":"{PornDoePremium - TheWhiteBoxxx} Sapphira - Beautiful Brunette Babe Sapphira In Hot Solo Action (08 May 2016) 720p\r\n\r\n\r\n\r\n\r\nGeneral info:\r\n\r\nSize: 215 Mb,\r\nDuration: 00: 11: 25,\r\nStreams: 2,\r\nFull bitrate: 2633 kb/s\r\nVideo: H264 (avc1), 1280x720, 29.97 fps\r\nAudio: AAC, STEREO, 44.1 kHz, 128 kb/s\r\n\r\nCategories:\r\n\r\nBabe, Brunette, European, HD Videos ,Masturbation, Solo\r\n\r\n\r\nTags:\r\n\r\nBeautiful, Black Hair, Couple Friendly, Erotica, European Pornstar, Fantasy, Female Friendly, Fingering, HD Porn, Solo Girl, The White Boxxx, Top Model\r\n\r\nScreenshot:\r\n \nhttp://imgdone.com/viewer.php?file=58419650793095359158.jpg\r\n\r\n\r\nFantasy becomes reality when ballerina Sapphire finishes her routine and starts fingering her pussy. This girl is so hot, it boggles the mind","torrent":{"xt":"urn:btih:676d4c34381773cad5adc45e6f1d6da987ed35e3","amp;dn":"+%7BPornDoePremium+-+TheWhiteBoxxx%7D+Sapphira+-+Beautiful+Brunette+","amp;tr":["udp%3A%2F%2Ftracker.leechers-paradise.org%3A6969","udp%3A%2F%2Fzer0day.ch%3A1337","udp%3A%2F%2Fopen.demonii.com%3A1337","udp%3A%2F%2Ftracker.coppersurfer.tk%3A6969","udp%3A%2F%2Fexodus.desync.com%3A6969"],"infoHash":"676d4c34381773cad5adc45e6f1d6da987ed35e3","infoHashBuffer":{"type":"Buffer","data":[103,109,76,52,56,23,115,202,213,173,196,94,111,29,109,169,135,237,53,227]},"announce":[],"urlList":[]}}