{"title":"Best of Blondes (Marc Dorcel) XXX NEW WEB-DL (2014)","uid":9598453,"size":1563807574,"categoryP":"porn","categoryS":"movies","magnet":"?xt=urn:btih:7017ce6310d477e5d6618e5f46c001265668ffe1&amp;dn=Best+of+Blondes+%28Marc+Dorcel%29+XXX+NEW+WEB-DL+%282014%29&amp;tr=udp%3A%2F%2Ftracker.openbittorrent.com%3A80&amp;tr=udp%3A%2F%2Fopen.demonii.com%3A1337&amp;tr=udp%3A%2F%2Ftracker.coppersurfer.tk%3A6969&amp;tr=udp%3A%2F%2Fexodus.desync.com%3A6969","seeders":1,"leechers":0,"uploader":"xuluhulu","files":1,"time":1392063798,"description":"Brown may be hot but the blondes are volcanic. Watch these real sex bombs literally explode with pleasure at the hands of their partners frantic kidneys.\n\nCOVERS:\n &lt;a href=&quot;\nhttp://imghoney.com/viewer.php?file=70627121393377984281.jpg&quot; rel=&quot;nofollow&quot; target=&quot;_NEW&quot;&gt;\nhttp://imghoney.com/viewer.php?file=70627121393377984281.jpg&lt;/a&gt;\n\n\nTHUMBSNAIL SCREENS:\n &lt;a href=&quot;\nhttp://imghoney.com/viewer.php?file=31211990569766771521.jpg&quot; rel=&quot;nofollow&quot; target=&quot;_NEW&quot;&gt;\nhttp://imghoney.com/viewer.php?file=31211990569766771521.jpg&lt;/a&gt;\n\n\nCAST:\n\nEllen Saint, Jane Darling, Jessica Fiorentino, Chrystal, Stacy Silver\n\n\nSEED &amp; ENJOY!!!","torrent":{"xt":"urn:btih:7017ce6310d477e5d6618e5f46c001265668ffe1","amp;dn":"Best+of+Blondes+%28Marc+Dorcel%29+XXX+NEW+WEB-DL+%282014%29","amp;tr":["udp%3A%2F%2Ftracker.openbittorrent.com%3A80","udp%3A%2F%2Fopen.demonii.com%3A1337","udp%3A%2F%2Ftracker.coppersurfer.tk%3A6969","udp%3A%2F%2Fexodus.desync.com%3A6969"],"infoHash":"7017ce6310d477e5d6618e5f46c001265668ffe1","infoHashBuffer":{"type":"Buffer","data":[112,23,206,99,16,212,119,229,214,97,142,95,70,192,1,38,86,104,255,225]},"announce":[],"urlList":[]}}