{"title":"AION-6 - Perfect Grey (2012) [mp3@320]","uid":7140339,"size":108497912,"categoryP":"audio","categoryS":"music","magnet":"?xt=urn:btih:76a7d31d3dbddfdd232fdfda94582c4ad8984621&amp;dn=AION-6+-+Perfect+Grey+%282012%29+%5Bmp3%40320%5D&amp;tr=udp%3A%2F%2Ftracker.openbittorrent.com%3A80&amp;tr=udp%3A%2F%2Fopen.demonii.com%3A1337&amp;tr=udp%3A%2F%2Ftracker.coppersurfer.tk%3A6969&amp;tr=udp%3A%2F%2Fexodus.desync.com%3A6969","seeders":1,"leechers":0,"uploader":"zibbik","files":16,"time":1332979471,"description":"Genre: Modern Metal / Melodic Death Metal\nOrigin: Russia\nFormat: 320 kbps\nTT: 44:48\n\n01. Below the clouds\n02. Perfect grey\n03. Ultimate nothing\n04. Obsession\n05. Insanity in me\n06. Release\n07. One day\n08. Out of heaven\n09. Far away\n10. Doesn`t matter\n11. Above the clouds \n\n\n\n","torrent":{"xt":"urn:btih:76a7d31d3dbddfdd232fdfda94582c4ad8984621","amp;dn":"AION-6+-+Perfect+Grey+%282012%29+%5Bmp3%40320%5D","amp;tr":["udp%3A%2F%2Ftracker.openbittorrent.com%3A80","udp%3A%2F%2Fopen.demonii.com%3A1337","udp%3A%2F%2Ftracker.coppersurfer.tk%3A6969","udp%3A%2F%2Fexodus.desync.com%3A6969"],"infoHash":"76a7d31d3dbddfdd232fdfda94582c4ad8984621","infoHashBuffer":{"type":"Buffer","data":[118,167,211,29,61,189,223,221,35,47,223,218,148,88,44,74,216,152,70,33]},"announce":[],"urlList":[]}}