{"title":"1Pondo - Hitomi oki - JAV - UNCENSORED","uid":9006072,"size":1925318032,"categoryP":"porn","categoryS":"hd___movies","magnet":"?xt=urn:btih:8fce7efe719b0cffd69100f21adcc2fec27bb438&amp;dn=1Pondo+-+Hitomi+oki+-+JAV+-+UNCENSORED&amp;tr=udp%3A%2F%2Ftracker.openbittorrent.com%3A80&amp;tr=udp%3A%2F%2Fopen.demonii.com%3A1337&amp;tr=udp%3A%2F%2Ftracker.coppersurfer.tk%3A6969&amp;tr=udp%3A%2F%2Fexodus.desync.com%3A6969","seeders":1,"leechers":1,"uploader":"sexmovies","files":1,"time":1381031203,"description":" &lt;a href=&quot;http://sexmovies.pro/view/746.jpg&quot; rel=&quot;nofollow&quot; target=&quot;_NEW&quot;&gt;http://sexmovies.pro/view/746.jpg&lt;/a&gt;\n\n&quot;Hitomi Oki Welcome to Himekore luxury soap&quot; 100513_673 off Hitomi Single Track\n1Pondo 100513_673 Princess Collection :: Hitomi oki\nJune 20, 1991: Date of Birth\nHometown: Ibaraki Prefecture\nHeight: 158cm\nWeight:\nBlood Type: A type\n3 Size: B88 W58 H86\nInterests: Anime","torrent":{"xt":"urn:btih:8fce7efe719b0cffd69100f21adcc2fec27bb438","amp;dn":"1Pondo+-+Hitomi+oki+-+JAV+-+UNCENSORED","amp;tr":["udp%3A%2F%2Ftracker.openbittorrent.com%3A80","udp%3A%2F%2Fopen.demonii.com%3A1337","udp%3A%2F%2Ftracker.coppersurfer.tk%3A6969","udp%3A%2F%2Fexodus.desync.com%3A6969"],"infoHash":"8fce7efe719b0cffd69100f21adcc2fec27bb438","infoHashBuffer":{"type":"Buffer","data":[143,206,126,254,113,155,12,255,214,145,0,242,26,220,194,254,194,123,180,56]},"announce":[],"urlList":[]}}