{"title":"PureMature - Nicole Aniston - july 2013","uid":8726004,"size":463857599,"categoryP":"porn","categoryS":"movies","magnet":"?xt=urn:btih:977b76a2eca05e28af606d7f695d69348c59aef9&amp;dn=PureMature+-+Nicole+Aniston+-+july+2013&amp;tr=udp%3A%2F%2Ftracker.openbittorrent.com%3A80&amp;tr=udp%3A%2F%2Fopen.demonii.com%3A1337&amp;tr=udp%3A%2F%2Ftracker.coppersurfer.tk%3A6969&amp;tr=udp%3A%2F%2Fexodus.desync.com%3A6969","seeders":1,"leechers":0,"uploader":null,"files":1,"time":1374515182,"description":"screens ----\n\n &lt;a href=&quot;\nhttp://imghorny.biz/share-03A3_51ED521E.html&quot; rel=&quot;nofollow&quot; target=&quot;_NEW&quot;&gt;\nhttp://imghorny.biz/share-03A3_51ED521E.html&lt;/a&gt;\n\n &lt;a href=&quot;\nhttp://imghorny.biz/share-926E_51ED5249.html&quot; rel=&quot;nofollow&quot; target=&quot;_NEW&quot;&gt;\nhttp://imghorny.biz/share-926E_51ED5249.html&lt;/a&gt;","torrent":{"xt":"urn:btih:977b76a2eca05e28af606d7f695d69348c59aef9","amp;dn":"PureMature+-+Nicole+Aniston+-+july+2013","amp;tr":["udp%3A%2F%2Ftracker.openbittorrent.com%3A80","udp%3A%2F%2Fopen.demonii.com%3A1337","udp%3A%2F%2Ftracker.coppersurfer.tk%3A6969","udp%3A%2F%2Fexodus.desync.com%3A6969"],"infoHash":"977b76a2eca05e28af606d7f695d69348c59aef9","infoHashBuffer":{"type":"Buffer","data":[151,123,118,162,236,160,94,40,175,96,109,127,105,93,105,52,140,89,174,249]},"announce":[],"urlList":[]}}