{"title":"My Chemical Romance - The Black Parade Is Dead + Bonus DVD","uid":4270842,"size":196321873,"categoryP":"audio","categoryS":"music","magnet":"?xt=urn:btih:9877c7d60f2c154cd5a4b709803e3a4ff0c09af6&amp;dn=My+Chemical+Romance+-+The+Black+Parade+Is+Dead+%2B+Bonus+DVD&amp;tr=udp%3A%2F%2Ftracker.openbittorrent.com%3A80&amp;tr=udp%3A%2F%2Fopen.demonii.com%3A1337&amp;tr=udp%3A%2F%2Ftracker.coppersurfer.tk%3A6969&amp;tr=udp%3A%2F%2Fexodus.desync.com%3A6969","seeders":1,"leechers":0,"uploader":"NOON3","files":34,"time":1214933728,"description":"CD:\n1.The End.  2:34\n2.Dead!  3:17\n3.This Is How I Disappear  3:51\n4.The Sharpest Lives  3:17\n5.Welcome to the Black Parade  5:05\n6.I Don&amp;#039;t Love You  3:47\n7.House of Wolves  3:38\n8.Interlude  1:01\n9.Cancer  3:16\n10.Mama  5:21\n11.Sleep  5:31\n12.Teenagers  3:03\n13.The Black Parade Is Dead  1:00\n14.Disenchanted  4:58\n15.Famous Last Words  5:09\n16.Blood  1:21\nDVD:\n1.Welcome to the Black Parade  5:11\n2.Thank You For The Venom  4:23\n3.Dead!  5:05\n4.The Sharpest Lives  4:40\n5.This Is How I Disappear  3:53\n6.Teenagers  4:07\n7.I&amp;#039;m Not Okay (I Promise)  4:05\n8.You Know What They Do to Guys Like Us in Prison  4:04\n9.Famous Last Words  5:08\n10.Give &amp;#039;Em Hell, Kid  2:45\n11.House of Wolves  3:42\n12.It&amp;#039;s Not a Fashion Statement, It&amp;#039;s a Death Wish  4:38\n13.I Don&amp;#039;t Love You  4:27\n14.(Untitled)  4:19\n15.Mama  4:45\n16.Helena  4:54\n17.Cancer  2:46\n\nAvg. bitrate: 202 kbps\n\nHave Fun and SEED!","torrent":{"xt":"urn:btih:9877c7d60f2c154cd5a4b709803e3a4ff0c09af6","amp;dn":"My+Chemical+Romance+-+The+Black+Parade+Is+Dead+%2B+Bonus+DVD","amp;tr":["udp%3A%2F%2Ftracker.openbittorrent.com%3A80","udp%3A%2F%2Fopen.demonii.com%3A1337","udp%3A%2F%2Ftracker.coppersurfer.tk%3A6969","udp%3A%2F%2Fexodus.desync.com%3A6969"],"infoHash":"9877c7d60f2c154cd5a4b709803e3a4ff0c09af6","infoHashBuffer":{"type":"Buffer","data":[152,119,199,214,15,44,21,76,213,164,183,9,128,62,58,79,240,192,154,246]},"announce":[],"urlList":[]}}