{"title":"Night Train to Lisbon 2013 720p BRRiP H264 AAC 5 1CH-BLiTZCRiEG","uid":9242360,"size":2151497228,"categoryP":"video","categoryS":"hd___movies","magnet":"?xt=urn:btih:a099aaff215fed2246eb76359f8684ceb01d8bde&amp;dn=Night+Train+to+Lisbon+2013+720p+BRRiP+H264+AAC+5+1CH-BLiTZCRiEG&amp;tr=udp%3A%2F%2Ftracker.openbittorrent.com%3A80&amp;tr=udp%3A%2F%2Fopen.demonii.com%3A1337&amp;tr=udp%3A%2F%2Ftracker.coppersurfer.tk%3A6969&amp;tr=udp%3A%2F%2Fexodus.desync.com%3A6969","seeders":1,"leechers":0,"uploader":"ronnie_88BOT","files":1,"time":1385300484,"description":"iNFOs : \n &lt;a href=&quot;\nhttp://nfomation.net/nfo.white/1385190886.night_train_lisbon_720p-blitz.txt.png&quot; rel=&quot;nofollow&quot; target=&quot;_NEW&quot;&gt;\nhttp://nfomation.net/nfo.white/1385190886.night_train_lisbon_720p-blitz.txt.png&lt;/a&gt;\n\n\nScreens : \n &lt;a href=&quot;\nhttp://s16.postimg.org/m2yyag4j9/1ex_TN6_Cd.png&quot; rel=&quot;nofollow&quot; target=&quot;_NEW&quot;&gt;\nhttp://s16.postimg.org/m2yyag4j9/1ex_TN6_Cd.png&lt;/a&gt; &lt;a href=&quot;\nhttp://s7.postimg.org/ma6f82tgr/Rw_A7yo_HF.png&quot; rel=&quot;nofollow&quot; target=&quot;_NEW&quot;&gt;\nhttp://s7.postimg.org/ma6f82tgr/Rw_A7yo_HF.png&lt;/a&gt;\n\n\nScreen Cap :\n &lt;a href=&quot;\nhttp://s22.postimg.org/7ayju2tpt/E33_Lk_OH.jpg&quot; rel=&quot;nofollow&quot; target=&quot;_NEW&quot;&gt;\nhttp://s22.postimg.org/7ayju2tpt/E33_Lk_OH.jpg&lt;/a&gt;","torrent":{"xt":"urn:btih:a099aaff215fed2246eb76359f8684ceb01d8bde","amp;dn":"Night+Train+to+Lisbon+2013+720p+BRRiP+H264+AAC+5+1CH-BLiTZCRiEG","amp;tr":["udp%3A%2F%2Ftracker.openbittorrent.com%3A80","udp%3A%2F%2Fopen.demonii.com%3A1337","udp%3A%2F%2Ftracker.coppersurfer.tk%3A6969","udp%3A%2F%2Fexodus.desync.com%3A6969"],"infoHash":"a099aaff215fed2246eb76359f8684ceb01d8bde","infoHashBuffer":{"type":"Buffer","data":[160,153,170,255,33,95,237,34,70,235,118,53,159,134,132,206,176,29,139,222]},"announce":[],"urlList":[]}}