{"title":"Star.Wars.COMPLETE.720p.HDTV.AAC.x264-JackBauer","uid":6502903,"size":17291559112,"categoryP":"video","categoryS":"hd___movies","magnet":"?xt=urn:btih:a8c511959ce402425180034a5c9eb18c6d26f03d&amp;dn=Star.Wars.COMPLETE.720p.HDTV.AAC.x264-JackBauer&amp;tr=udp%3A%2F%2Ftracker.openbittorrent.com%3A80&amp;tr=udp%3A%2F%2Fopen.demonii.com%3A1337&amp;tr=udp%3A%2F%2Ftracker.coppersurfer.tk%3A6969&amp;tr=udp%3A%2F%2Fexodus.desync.com%3A6969","seeders":1,"leechers":0,"uploader":"Mikey320","files":24,"time":1309316470,"description":"SOURCE:............................:HDTV\nLANGUAGE:.......................:English\nCONTAINER:..........................:MP4\nRESOLUTION:..............:1280x544@25fps\nVIDEO CODEC:.......................:x264\nAUDIO BITRATE:..............:&lt;a class=&quot;__cf_email__&quot; href=&quot;/cdn-cgi/l/email-protection&quot; data-cfemail=&quot;bc8e8e8cf7decccffc89928d&quot;&gt;[email&amp;#160;protected]&lt;/a&gt;&lt;script cf-hash='f9e31' type=&quot;text/javascript&quot;&gt;\n/* &lt;![CDATA[ */!function(){try{var t=&quot;currentScript&quot;in document?document.currentScript:function(){for(var t=document.getElementsByTagName(&quot;script&quot;),e=t.length;e--;)if(t[e].getAttribute(&quot;cf-hash&quot;))return t[e]}();if(t&amp;&amp;t.previousSibling){var e,r,n,i,c=t.previousSibling,a=c.getAttribute(&quot;data-cfemail&quot;);if(a){for(e=&quot;&quot;,r=parseInt(a.substr(0,2),16),n=2;a.length-n;n+=2)i=parseInt(a.substr(n,2),16)^r,e+=String.fromCharCode(i);e=document.createTextNode(e),c.parentNode.replaceChild(e,c)}}}catch(u){}}();/* ]]&gt; */&lt;/script&gt;\nAUDIO CODEC:...................:Nero AAC","torrent":{"xt":"urn:btih:a8c511959ce402425180034a5c9eb18c6d26f03d","amp;dn":"Star.Wars.COMPLETE.720p.HDTV.AAC.x264-JackBauer","amp;tr":["udp%3A%2F%2Ftracker.openbittorrent.com%3A80","udp%3A%2F%2Fopen.demonii.com%3A1337","udp%3A%2F%2Ftracker.coppersurfer.tk%3A6969","udp%3A%2F%2Fexodus.desync.com%3A6969"],"infoHash":"a8c511959ce402425180034a5c9eb18c6d26f03d","infoHashBuffer":{"type":"Buffer","data":[168,197,17,149,156,228,2,66,81,128,3,74,92,158,177,140,109,38,240,61]},"announce":[],"urlList":[]}}