{"title":"Alex Jones Show - 2010 May 06 TH [sebaygo1]","uid":5539826,"size":87733901,"categoryP":"audio","categoryS":"other","magnet":"?xt=urn:btih:a8dc2f3c0cb39602472c760a82ae9327e6070d34&amp;dn=Alex+Jones+Show+-+2010+May+06+TH+%5Bsebaygo1%5D&amp;tr=udp%3A%2F%2Ftracker.openbittorrent.com%3A80&amp;tr=udp%3A%2F%2Fopen.demonii.com%3A1337&amp;tr=udp%3A%2F%2Ftracker.coppersurfer.tk%3A6969&amp;tr=udp%3A%2F%2Fexodus.desync.com%3A6969","seeders":1,"leechers":0,"uploader":"sebaygo1","files":13,"time":1273185757,"description":".\n\t\t\t\t\t\t\t\nThe Alex Jones Show\nThursday, 06 May 2010\n\n\n[sebaygo1]\n\n\n\nScheduled Guests\n................\n\n[show description from the Infowars web site]\n\n\nAlex talks [hour 3, much of hour 4] with activist Red Beckman, father of the Fully Informed Jury Association and co-author of The Law That Never Was: The Fraud of the 16th Amendment and Personal Income Tax. \n &lt;a href=&quot;\nhttp://www.fija.org/&quot; rel=&quot;nofollow&quot; target=&quot;_NEW&quot;&gt;\nhttp://www.fija.org/&lt;/a&gt; &lt;a href=&quot;\nhttp://en.wikipedia.org/wiki/Fully_Informed_Jury_Association&quot; rel=&quot;nofollow&quot; target=&quot;_NEW&quot;&gt;\nhttp://en.wikipedia.org/wiki/Fully_Informed_Jury_Association&lt;/a&gt; &lt;a href=&quot;\nhttp://en.wikipedia.org/wiki/The_Law_that_Never_Was&quot; rel=&quot;nofollow&quot; target=&quot;_NEW&quot;&gt;\nhttp://en.wikipedia.org/wiki/The_Law_that_Never_Was&lt;/a&gt; &lt;a href=&quot;\nhttp://video.google.com/videoplay?docid=2889520400972187394#&quot; rel=&quot;nofollow&quot; target=&quot;_NEW&quot;&gt;\nhttp://video.google.com/videoplay?docid=2889520400972187394#&lt;/a&gt;\n\n\n\n\nAlex also talks [1st half of hour 2] with Godfrey Bloom, member of the European Parliament for Yorkshire and the Humber, about Nigel Farage's air plane crash and elections. \n &lt;a href=&quot;\nhttp://www.godfreybloommep.co.uk/&quot; rel=&quot;nofollow&quot; target=&quot;_NEW&quot;&gt;\nhttp://www.godfreybloommep.co.uk/&lt;/a&gt; &lt;a href=&quot;\nhttp://www.europarl.europa.eu/members/expert/alphaOrder/view.do?language=EN&amp;id=28513&quot; rel=&quot;nofollow&quot; target=&quot;_NEW&quot;&gt;\nhttp://www.europarl.europa.eu/members/expert/alphaOrder/view.do?language=EN&amp;id=28513&lt;/a&gt; &lt;a href=&quot;\nhttp://blog.godfreybloommep.co.uk/&quot; rel=&quot;nofollow&quot; target=&quot;_NEW&quot;&gt;\nhttp://blog.godfreybloommep.co.uk/&lt;/a&gt; &lt;a href=&quot;\nhttp://en.wikipedia.org/wiki/Godfrey_Bloom&quot; rel=&quot;nofollow&quot; target=&quot;_NEW&quot;&gt;\nhttp://en.wikipedia.org/wiki/Godfrey_Bloom&lt;/a&gt;\n\n\n\nAlex also discusses the issues of the day and takes a number of calls.\n\n[Steve Shenk from sponsor, eFoodsDirect, does a lengthy &quot;live commercial&quot; with Alex during 2nd half of hour 2.]\n\n[Ted Anderson -- owner of GCN radio network -- is in-studio for several minutes in the 2nd half of hour 3, doing a &quot;live commercial&quot; for his gold business, Midas Resources]\n\n\n\n#%#%#%#%#%#%#%#%#%#%#%#%#%#%#%#%#%#%#%#%#%#%#%#%#%#%#\nNot able to find a torrent of mine where or when you \nexpected it?\nCheck out my torrents blog for info about what I am\nuploading, tracker problems, etc..\n\nSome sites will not allow a blogspot URL in an \nuploaded torrent's description, so I have included \nthe blog's web address in a file included with this\ntorrent named:\nsebaygo1_torrents_info_PLEASE-READ.txt\n#%#%#%#%#%#%#%#%#%#%#%#%#%#%#%#%#%#%#%#%#%#%#%#%#%#%#\n\n\n\n_/_/_/_/_/_/_/_/_/_/_/_/_/_/_/_/_/_/_/_/_/_/_/_/_/_/_/_/_/_/_/_/_/_/\n\n It is my opinion that in this time it is virtually\n essential to seek information from a variety of sources, \n to listen to a spectrum of voices in order to better \n understand the &quot;big picture.&quot; A reliance solely upon\n mainstream corporate media for news and info is a \n prescription for ignorance. I try to share information\n that counters the monotone of mainstream corporate media.\n \n NOTE: The material here is made available strictly as\n information. Do not assume support or endorsement on my\n part of the contents. \n\n Think for yourself!\n To paraphrase the late William Cooper: \n Read everything, listen to everything, but believe nothing \n until you've researched it yourself.\n\n_/_/_/_/_/_/_/_/_/_/_/_/_/_/_/_/_/_/_/_/_/_/_/_/_/_/_/_/_/_/_/\n.","torrent":{"xt":"urn:btih:a8dc2f3c0cb39602472c760a82ae9327e6070d34","amp;dn":"Alex+Jones+Show+-+2010+May+06+TH+%5Bsebaygo1%5D","amp;tr":["udp%3A%2F%2Ftracker.openbittorrent.com%3A80","udp%3A%2F%2Fopen.demonii.com%3A1337","udp%3A%2F%2Ftracker.coppersurfer.tk%3A6969","udp%3A%2F%2Fexodus.desync.com%3A6969"],"infoHash":"a8dc2f3c0cb39602472c760a82ae9327e6070d34","infoHashBuffer":{"type":"Buffer","data":[168,220,47,60,12,179,150,2,71,44,118,10,130,174,147,39,230,7,13,52]},"announce":[],"urlList":[]}}