{"title":"BATWING 05. DC 2012","uid":6932216,"size":15163992,"categoryP":"other","categoryS":"comics","magnet":"?xt=urn:btih:ad193528b4a460e9a65a5db2b439235b0d5c2331&amp;dn=BATWING+05.+DC+2012&amp;tr=udp%3A%2F%2Ftracker.openbittorrent.com%3A80&amp;tr=udp%3A%2F%2Fopen.demonii.com%3A1337&amp;tr=udp%3A%2F%2Ftracker.coppersurfer.tk%3A6969&amp;tr=udp%3A%2F%2Fexodus.desync.com%3A6969","seeders":1,"leechers":0,"uploader":"wowcabbage","files":1,"time":1325696856,"description":"BATWING 05. DC 2012","torrent":{"xt":"urn:btih:ad193528b4a460e9a65a5db2b439235b0d5c2331","amp;dn":"BATWING+05.+DC+2012","amp;tr":["udp%3A%2F%2Ftracker.openbittorrent.com%3A80","udp%3A%2F%2Fopen.demonii.com%3A1337","udp%3A%2F%2Ftracker.coppersurfer.tk%3A6969","udp%3A%2F%2Fexodus.desync.com%3A6969"],"infoHash":"ad193528b4a460e9a65a5db2b439235b0d5c2331","infoHashBuffer":{"type":"Buffer","data":[173,25,53,40,180,164,96,233,166,90,93,178,180,57,35,91,13,92,35,49]},"announce":[],"urlList":[]}}