{"title":"The.Colbert.Report.2013.12.02.Daniel.Goleman.720p.HDTV.x264-LMAO","uid":9288440,"size":570895730,"categoryP":"video","categoryS":"hd___tv_shows","magnet":"?xt=urn:btih:aed5f6ec72ae0e7132bd907e508550d27da9a88c&amp;dn=The.Colbert.Report.2013.12.02.Daniel.Goleman.720p.HDTV.x264-LMAO&amp;tr=udp%3A%2F%2Ftracker.openbittorrent.com%3A80&amp;tr=udp%3A%2F%2Fopen.demonii.com%3A1337&amp;tr=udp%3A%2F%2Ftracker.coppersurfer.tk%3A6969&amp;tr=udp%3A%2F%2Fexodus.desync.com%3A6969","seeders":1,"leechers":1,"uploader":"sceneline","files":16,"time":1386052556,"description":"Please Seed back to make the speed Faster!!\nand use comment \n ............ NFO .............\n-","torrent":{"xt":"urn:btih:aed5f6ec72ae0e7132bd907e508550d27da9a88c","amp;dn":"The.Colbert.Report.2013.12.02.Daniel.Goleman.720p.HDTV.x264-LMAO","amp;tr":["udp%3A%2F%2Ftracker.openbittorrent.com%3A80","udp%3A%2F%2Fopen.demonii.com%3A1337","udp%3A%2F%2Ftracker.coppersurfer.tk%3A6969","udp%3A%2F%2Fexodus.desync.com%3A6969"],"infoHash":"aed5f6ec72ae0e7132bd907e508550d27da9a88c","infoHashBuffer":{"type":"Buffer","data":[174,213,246,236,114,174,14,113,50,189,144,126,80,133,80,210,125,169,168,140]},"announce":[],"urlList":[]}}