{"title":"[Private] Jane Darling, Barbara Summer, Lucy Love, Maya Gold, K","uid":15012859,"size":214452356,"categoryP":"porn","categoryS":"other","magnet":"?xt=urn:btih:b5fcc37d4095fd0085f533e37a536391eb738c90&amp;dn=+%5BPrivate%5D+Jane+Darling%2C+Barbara+Summer%2C+Lucy+Love%2C+Maya+Gold%2C+K&amp;tr=udp%3A%2F%2Ftracker.leechers-paradise.org%3A6969&amp;tr=udp%3A%2F%2Fzer0day.ch%3A1337&amp;tr=udp%3A%2F%2Fopen.demonii.com%3A1337&amp;tr=udp%3A%2F%2Ftracker.coppersurfer.tk%3A6969&amp;tr=udp%3A%2F%2Fexodus.desync.com%3A6969","seeders":1,"leechers":0,"uploader":"LucasCar","files":3,"time":1466439643,"description":"[Private] Jane Darling, Barbara Summer, Lucy Love, Maya Gold, Kirsty Ronita - 10 People Orgy at the Gym’s Machines Room [XXX] \r\n \nhttp://imgteen.org/img-5767fbd9374f7.html\r\n\r\n\r\n\r\n★ ★ ★  For more Exclusive Porn please visit ★ ★ ★\r\n \nhttps://thepiratebay.org/user/LucasCar","torrent":{"xt":"urn:btih:b5fcc37d4095fd0085f533e37a536391eb738c90","amp;dn":"+%5BPrivate%5D+Jane+Darling%2C+Barbara+Summer%2C+Lucy+Love%2C+Maya+Gold%2C+K","amp;tr":["udp%3A%2F%2Ftracker.leechers-paradise.org%3A6969","udp%3A%2F%2Fzer0day.ch%3A1337","udp%3A%2F%2Fopen.demonii.com%3A1337","udp%3A%2F%2Ftracker.coppersurfer.tk%3A6969","udp%3A%2F%2Fexodus.desync.com%3A6969"],"infoHash":"b5fcc37d4095fd0085f533e37a536391eb738c90","infoHashBuffer":{"type":"Buffer","data":[181,252,195,125,64,149,253,0,133,245,51,227,122,83,99,145,235,115,140,144]},"announce":[],"urlList":[]}}