{"title":"[House] MC ZHAN - MCDJ PARTY 043","uid":7076339,"size":154319558,"categoryP":"audio","categoryS":"music","magnet":"?xt=urn:btih:baf961440db14075055db2651b55e010e855dd67&amp;dn=%5BHouse%5D+MC+ZHAN+-+MCDJ+PARTY+043&amp;tr=udp%3A%2F%2Ftracker.openbittorrent.com%3A80&amp;tr=udp%3A%2F%2Fopen.demonii.com%3A1337&amp;tr=udp%3A%2F%2Ftracker.coppersurfer.tk%3A6969&amp;tr=udp%3A%2F%2Fexodus.desync.com%3A6969","seeders":1,"leechers":0,"uploader":"promoparty","files":-1,"time":1330861469,"description":"================================================================[DJ4U.ru]===\n\nMC ZHAN - MCDJ PARTY 043\n\nGenre: House\nDate: 03.03.2012\nOffsite: http://mcdj.ru\n\n01. Crookers - Royal T Ft. Roisin Murphy\n02. Knife Party - Internet Friends (Original Mix)\n03. Groove Armada vs Phonic Funk I See You Baby DJ Nejtrino DJ Baur Mashup\n04. Fedde Le Grand vs Nirvana - Back  Forth Spirit (Alex Gaudino  Jason Rooney Bootleg)\n05. Swedish House Mafia Vs Knife Party - Antidote (Original Mix)\n06. Dave Floyd feat. Dj Wise D  Dj Kobe - Magic People Voodoo People (Original Mix)\n07. Axwell Peter Luts Sunfreakz ft. Andrea Britton Counting Down The Days In Cayo Anton Liss\n08. Andrey Sher, Gloria House - Lost Her Ways (Jay Mexx Remix)\n09. Chemical Bros vs Plastic Funk - Galvanize Baby (DJ Nejtrino vs DJ Baur Mash Up)\n10. Black Eyed Peas - Let's Get It Started (Danny Rush Remix)\n11. Christopher S Feat. Max Urban - Star (Mike Candys Remix)\n12. Bob Sinclar Adamski vs. Avicii Mattias G80s New Killer\n13. Dj Zinc vs Nirvana - Nexx Like The Teen Spirit (dj forrest bootleg mix)\n14. DJs From Mars  Fragma - Insane (In Da Brain) (Original Club Mix)\n15. Cristian Marchi &amp; Syke'n'Sugarstarr Feat. Lisa Millett - U Got Me Rockin' (Syke'n'Sugarstarr Bouncy Mix)\n16. Polina Griffith, Ralph Good - SOS (Tujamo Remix)\n17. Missy Elliot vs Don Diablo Get Ya Freak On DJ Nejtrino DJ Baur Mashup\n18. Michael Jackson vs Belocca Let The Black White Alex Milano Mashup\n19. Peter Gelderblom feat. Dominica - I Gotta Let U Go (Tujamo Remix)\n20. Tiesto  Diplo VS Far East Movement - Cmon Like A G6 (Dulava Mashup)\n\n=============================================================================\nDownload or subscribe to free podcast episodes from MC ZHAN on iTunes!  &lt;a href=&quot;\nhttp://itunes.apple.com/ru/podcast/id439599080&quot; rel=&quot;nofollow&quot; target=&quot;_NEW&quot;&gt;\nhttp://itunes.apple.com/ru/podcast/id439599080&lt;/a&gt;","torrent":{"xt":"urn:btih:baf961440db14075055db2651b55e010e855dd67","amp;dn":"%5BHouse%5D+MC+ZHAN+-+MCDJ+PARTY+043","amp;tr":["udp%3A%2F%2Ftracker.openbittorrent.com%3A80","udp%3A%2F%2Fopen.demonii.com%3A1337","udp%3A%2F%2Ftracker.coppersurfer.tk%3A6969","udp%3A%2F%2Fexodus.desync.com%3A6969"],"infoHash":"baf961440db14075055db2651b55e010e855dd67","infoHashBuffer":{"type":"Buffer","data":[186,249,97,68,13,177,64,117,5,93,178,101,27,85,224,16,232,85,221,103]},"announce":[],"urlList":[]}}