{"title":"Closed Circuit (2013) 720p BluRay - 700MB - ShAaNiG","uid":9389303,"size":734127438,"categoryP":"video","categoryS":"movies","magnet":"?xt=urn:btih:bdc3db8e3a98eb581e07ca62c65fba12baab9823&amp;dn=Closed+Circuit+%282013%29+720p+BluRay+-+700MB+-+ShAaNiG&amp;tr=udp%3A%2F%2Ftracker.openbittorrent.com%3A80&amp;tr=udp%3A%2F%2Fopen.demonii.com%3A1337&amp;tr=udp%3A%2F%2Ftracker.coppersurfer.tk%3A6969&amp;tr=udp%3A%2F%2Fexodus.desync.com%3A6969","seeders":1,"leechers":0,"uploader":"ShAaNiG","files":-1,"time":1387852493,"description":"--------------------------------------------------------------------\n--------------------------------------------------------------------\n\n        ShAaNiG.com - High quality movies at smallest size\n\n\n                    &lt;a href=&quot; http://www.shaanig.com&quot; rel=&quot;nofollow&quot; target=&quot;_NEW&quot;&gt; http://www.shaanig.com&lt;/a&gt;\n\n\n        English and Hindi both new and old movies available.\n\n--------------------------------------------------------------------\n--------------------------------------------------------------------\n\n\n\nRELEASENOTES:\n\n[TITLE]:........................[ Closed Circuit\n[DIRECTOR]:.....................[ John Crowley\n[RELEASE DATE]:.................[ 28 August 2013 (USA)\n[GENRE]:........................[ Crime | Drama | Mystery\n[HDTV SUPPORT]:.................[ Yes\n[NO OF FILES]:..................[ 1\n[VIDEO]:........................[ MKV - x264\n[AUDIO]:........................[ AAC - 2CH\n[FILE SIZE]:....................[ 700MB\n[RESOLUTION]:...................[ 1280x536\n[FRAME RATE]:...................[ 23.976 fps\n[LANGUAGE]:.....................[ English\n[SUBTITLES]:....................[ English [Softcoded] - muxed\n[RUNTIME]:......................[ 01:36:02\n[ENCODER]:......................[ ShAaNiG\n[SOURCE]:.......................[ 720p.BluRay-AMIABLE\n\n\nSCREENSHOTS:\n &lt;a href=&quot;\nhttp://www.megaimg.com/viewer.php?file=10382310828633540326.jpg&quot; rel=&quot;nofollow&quot; target=&quot;_NEW&quot;&gt;\nhttp://www.megaimg.com/viewer.php?file=10382310828633540326.jpg&lt;/a&gt;\n &lt;a href=&quot;\nhttp://www.megaimg.com/viewer.php?file=34877718839802775053.jpg&quot; rel=&quot;nofollow&quot; target=&quot;_NEW&quot;&gt;\nhttp://www.megaimg.com/viewer.php?file=34877718839802775053.jpg&lt;/a&gt;\n &lt;a href=&quot;\nhttp://www.megaimg.com/viewer.php?file=84187370010299151325.jpg&quot; rel=&quot;nofollow&quot; target=&quot;_NEW&quot;&gt;\nhttp://www.megaimg.com/viewer.php?file=84187370010299151325.jpg&lt;/a&gt;\n &lt;a href=&quot;\nhttp://www.megaimg.com/viewer.php?file=42047505025755791793.jpg&quot; rel=&quot;nofollow&quot; target=&quot;_NEW&quot;&gt;\nhttp://www.megaimg.com/viewer.php?file=42047505025755791793.jpg&lt;/a&gt;\n &lt;a href=&quot;\nhttp://www.megaimg.com/viewer.php?file=88757385300839460604.jpg&quot; rel=&quot;nofollow&quot; target=&quot;_NEW&quot;&gt;\nhttp://www.megaimg.com/viewer.php?file=88757385300839460604.jpg&lt;/a&gt;\n &lt;a href=&quot;\nhttp://www.megaimg.com/viewer.php?file=34875972450433134961.jpg&quot; rel=&quot;nofollow&quot; target=&quot;_NEW&quot;&gt;\nhttp://www.megaimg.com/viewer.php?file=34875972450433134961.jpg&lt;/a&gt;","torrent":{"xt":"urn:btih:bdc3db8e3a98eb581e07ca62c65fba12baab9823","amp;dn":"Closed+Circuit+%282013%29+720p+BluRay+-+700MB+-+ShAaNiG","amp;tr":["udp%3A%2F%2Ftracker.openbittorrent.com%3A80","udp%3A%2F%2Fopen.demonii.com%3A1337","udp%3A%2F%2Ftracker.coppersurfer.tk%3A6969","udp%3A%2F%2Fexodus.desync.com%3A6969"],"infoHash":"bdc3db8e3a98eb581e07ca62c65fba12baab9823","infoHashBuffer":{"type":"Buffer","data":[189,195,219,142,58,152,235,88,30,7,202,98,198,95,186,18,186,171,152,35]},"announce":[],"urlList":[]}}