{"title":"Cave Girl Comics 1952 Magazine Enterprises","uid":8775672,"size":96232250,"categoryP":"other","categoryS":"comics","magnet":"?xt=urn:btih:c46650c6d28598dd2090c759d940430944f82dff&amp;dn=Cave+Girl+Comics+1952+Magazine+Enterprises&amp;tr=udp%3A%2F%2Ftracker.openbittorrent.com%3A80&amp;tr=udp%3A%2F%2Fopen.demonii.com%3A1337&amp;tr=udp%3A%2F%2Ftracker.coppersurfer.tk%3A6969&amp;tr=udp%3A%2F%2Fexodus.desync.com%3A6969","seeders":1,"leechers":0,"uploader":"Mothra67","files":-1,"time":1375551111,"description":"Carol lost her parents to an attack by the savage Balu natives of the African Jungle. She manages to escape death when an eagle carried her away. The eagle drops the girl in the Dawn Lands. The Dawn Lands are a valley hidden by the mountains known as the Barriers of the Moon which was lost to time. Carol is raised by wolves and became Cave Girl, but after the leader Kattu dies Cave Girl becomes leader of the pack. She was skilled in using a bow, spear and knife and also could speak to animals. She learned how to use weapons from watching the Hairy Men, a group of Neanderthals who lived in the Dawn Lands. Their king Pood wanted Cave Girl for himself, but she did not want anything to do with him and fought back slaying the Hairy Men. Later, explorer Luke Hardin enter the valley and became her boyfriend. Cave Girl was also assisted by a Pygmy outcast named Bobo.\n\nReal Name\nCarol London\nFirst Appearance\nThun'da #2 (1952)\nOriginal Publisher\nMagazine Enterprises\nCreated by\nGardner Fox and Bob Powell\n\nseed for all to enjoy!","torrent":{"xt":"urn:btih:c46650c6d28598dd2090c759d940430944f82dff","amp;dn":"Cave+Girl+Comics+1952+Magazine+Enterprises","amp;tr":["udp%3A%2F%2Ftracker.openbittorrent.com%3A80","udp%3A%2F%2Fopen.demonii.com%3A1337","udp%3A%2F%2Ftracker.coppersurfer.tk%3A6969","udp%3A%2F%2Fexodus.desync.com%3A6969"],"infoHash":"c46650c6d28598dd2090c759d940430944f82dff","infoHashBuffer":{"type":"Buffer","data":[196,102,80,198,210,133,152,221,32,144,199,89,217,64,67,9,68,248,45,255]},"announce":[],"urlList":[]}}