{"title":"casablanca subtitulos español","uid":7378417,"size":105545,"categoryP":"video","categoryS":"other","magnet":"?xt=urn:btih:c94dfa46d54f234b5c1de0d23ddbae11d2804c12&amp;dn=casablanca+subtitulos+espa%26ntilde%3Bol&amp;tr=udp%3A%2F%2Ftracker.openbittorrent.com%3A80&amp;tr=udp%3A%2F%2Fopen.demonii.com%3A1337&amp;tr=udp%3A%2F%2Ftracker.coppersurfer.tk%3A6969&amp;tr=udp%3A%2F%2Fexodus.desync.com%3A6969","seeders":1,"leechers":0,"uploader":"utnmartin","files":1,"time":1340432651,"description":"Son los subtitulos para la pelicula casablanca.","torrent":{"xt":"urn:btih:c94dfa46d54f234b5c1de0d23ddbae11d2804c12","amp;dn":"casablanca+subtitulos+espa%26ntilde%3Bol","amp;tr":["udp%3A%2F%2Ftracker.openbittorrent.com%3A80","udp%3A%2F%2Fopen.demonii.com%3A1337","udp%3A%2F%2Ftracker.coppersurfer.tk%3A6969","udp%3A%2F%2Fexodus.desync.com%3A6969"],"infoHash":"c94dfa46d54f234b5c1de0d23ddbae11d2804c12","infoHashBuffer":{"type":"Buffer","data":[201,77,250,70,213,79,35,75,92,29,224,210,61,219,174,17,210,128,76,18]},"announce":[],"urlList":[]}}