{"title":"Block.Party.UNRATED.DVDRip.XViD-NeDiVx","uid":6927605,"size":1523264057,"categoryP":"video","categoryS":"movies","magnet":"?xt=urn:btih:ca7b8267062debe60aaf92c905880fbe49565087&amp;dn=Block.Party.UNRATED.DVDRip.XViD-NeDiVx&amp;tr=udp%3A%2F%2Ftracker.openbittorrent.com%3A80&amp;tr=udp%3A%2F%2Fopen.demonii.com%3A1337&amp;tr=udp%3A%2F%2Ftracker.coppersurfer.tk%3A6969&amp;tr=udp%3A%2F%2Fexodus.desync.com%3A6969","seeders":1,"leechers":0,"uploader":"TvTeam","files":10,"time":1325564430,"description":". \n &lt;a href=&quot;\nhttp://www.torrenting.com&quot; rel=&quot;nofollow&quot; target=&quot;_NEW&quot;&gt;\nhttp://www.torrenting.com&lt;/a&gt;          :     Once &amp; For all ;)\n\n\n               www . Torrenting . Com \n\n(((((((((((((= Enjoy No RAR releases =))))))))))))))))))))\n\n\n...................................NFO:....................................\n\n.Block.Party.UNRATED.DVDRip.XViD-NeDiVx &lt;a href=&quot;\nhttp://www.imdb.com/title/tt0425598/&quot; rel=&quot;nofollow&quot; target=&quot;_NEW&quot;&gt;\nhttp://www.imdb.com/title/tt0425598/&lt;/a&gt;\nunrated\nvid: 640*352\ntime: 109m 55s\naudio: ac3 5.1","torrent":{"xt":"urn:btih:ca7b8267062debe60aaf92c905880fbe49565087","amp;dn":"Block.Party.UNRATED.DVDRip.XViD-NeDiVx","amp;tr":["udp%3A%2F%2Ftracker.openbittorrent.com%3A80","udp%3A%2F%2Fopen.demonii.com%3A1337","udp%3A%2F%2Ftracker.coppersurfer.tk%3A6969","udp%3A%2F%2Fexodus.desync.com%3A6969"],"infoHash":"ca7b8267062debe60aaf92c905880fbe49565087","infoHashBuffer":{"type":"Buffer","data":[202,123,130,103,6,45,235,230,10,175,146,201,5,136,15,190,73,86,80,135]},"announce":[],"urlList":[]}}