{"title":"SexuallyBroken 16 09 30 Nadia White XXX 720p MP4-MiST","uid":15947250,"size":661772689,"categoryP":"porn","categoryS":"movie_clips","magnet":"?xt=urn:btih:d86f1ce09478a45aa211a9f4be2ff26144342e39&amp;dn=SexuallyBroken+16+09+30+Nadia+White+XXX+720p+MP4-MiST&amp;tr=udp%3A%2F%2Ftracker.leechers-paradise.org%3A6969&amp;tr=udp%3A%2F%2Fzer0day.ch%3A1337&amp;tr=udp%3A%2F%2Fopen.demonii.com%3A1337&amp;tr=udp%3A%2F%2Ftracker.coppersurfer.tk%3A6969&amp;tr=udp%3A%2F%2Fexodus.desync.com%3A6969","seeders":1,"leechers":3,"uploader":"JohnDevicariis","files":3,"time":1475524714,"description":"\n\n  Image Links \t:  http://imgbonk.com/image/5LRkR  \n\n  Image Links \t:  http://imgbonk.com/image/5LSb4  \n\n  Image Sheet \t:  http://imgshag.com/image/fgzWp \n\n \t \t \t Get More Small Sized XXX Videos \n \n \t   https://thepiratebay.se/user/johndevicariis/506","torrent":{"xt":"urn:btih:d86f1ce09478a45aa211a9f4be2ff26144342e39","amp;dn":"SexuallyBroken+16+09+30+Nadia+White+XXX+720p+MP4-MiST","amp;tr":["udp%3A%2F%2Ftracker.leechers-paradise.org%3A6969","udp%3A%2F%2Fzer0day.ch%3A1337","udp%3A%2F%2Fopen.demonii.com%3A1337","udp%3A%2F%2Ftracker.coppersurfer.tk%3A6969","udp%3A%2F%2Fexodus.desync.com%3A6969"],"infoHash":"d86f1ce09478a45aa211a9f4be2ff26144342e39","infoHashBuffer":{"type":"Buffer","data":[216,111,28,224,148,120,164,90,162,17,169,244,190,47,242,97,68,52,46,57]},"announce":[],"urlList":[]}}