{"title":"50 Near Naked Suicide Girl Galadriell - Scarlet Dreams - Set 615","uid":15464698,"size":76521034,"categoryP":"other","categoryS":"pictures","magnet":"?xt=urn:btih:d922a5e404b933e793f833c86d10a384491839a6&amp;dn=50+Near+Naked+Suicide+Girl+Galadriell+-+Scarlet+Dreams+-+Set+615&amp;tr=udp%3A%2F%2Ftracker.leechers-paradise.org%3A6969&amp;tr=udp%3A%2F%2Fzer0day.ch%3A1337&amp;tr=udp%3A%2F%2Fopen.demonii.com%3A1337&amp;tr=udp%3A%2F%2Ftracker.coppersurfer.tk%3A6969&amp;tr=udp%3A%2F%2Fexodus.desync.com%3A6969","seeders":1,"leechers":0,"uploader":"samcode4u","files":52,"time":1470084152,"description":"[b]Desktop Wallpapers - [ECLiPSE]\r\n\r\n50 Pics | [Mixed]\r\n\r\n##############$=- Preview -=$##############\r\nClick on a link to view image in original resolution (HD):\r\n \nhttps://i1.imgpile.com/2016/08/01/2d7b748893da23305c9d528c91055a83.jpg \nhttps://i2.imgpile.com/2016/08/01/c7cbe7586e2a16274a8bc72125b0491f.jpg \nhttps://i1.imgpile.com/2016/08/01/709d16774e74e3235189c394880eeb69.jpg \nhttps://i2.imgpile.com/2016/08/01/64fb3119ef424ce57d2b331710a52eea.jpg","torrent":{"xt":"urn:btih:d922a5e404b933e793f833c86d10a384491839a6","amp;dn":"50+Near+Naked+Suicide+Girl+Galadriell+-+Scarlet+Dreams+-+Set+615","amp;tr":["udp%3A%2F%2Ftracker.leechers-paradise.org%3A6969","udp%3A%2F%2Fzer0day.ch%3A1337","udp%3A%2F%2Fopen.demonii.com%3A1337","udp%3A%2F%2Ftracker.coppersurfer.tk%3A6969","udp%3A%2F%2Fexodus.desync.com%3A6969"],"infoHash":"d922a5e404b933e793f833c86d10a384491839a6","infoHashBuffer":{"type":"Buffer","data":[217,34,165,228,4,185,51,231,147,248,51,200,109,16,163,132,73,24,57,166]},"announce":[],"urlList":[]}}