{"title":"Soul Heaven Lyrics (2012)","uid":7334386,"size":360384794,"categoryP":"audio","categoryS":"music","magnet":"?xt=urn:btih:e494dab4fa3ad16a2a845387ab648e4c6b6d3860&amp;dn=Soul+Heaven+Lyrics+%282012%29&amp;tr=udp%3A%2F%2Ftracker.openbittorrent.com%3A80&amp;tr=udp%3A%2F%2Fopen.demonii.com%3A1337&amp;tr=udp%3A%2F%2Ftracker.coppersurfer.tk%3A6969&amp;tr=udp%3A%2F%2Fexodus.desync.com%3A6969","seeders":1,"leechers":0,"uploader":"leslosman","files":-1,"time":1339023089,"description":"Soul Heaven Lyrics (2012)\n\nArtist: VA\nDate: 2012\nGenre: Chill, Instrumental, Longe, Soul\nQuality: mp3, 320 kbps\nTracks: 33\nSize: 345 Mb\n\n  Tracklist\n\n01 - Birdy-People Help The People\n02 - Sunlounger feat. Zara-B. Crawling (Original Mix)\n03 - Brian-Drowning (Acoustic Version)\n04 - Blank &amp; Jones with Jason Caesar-Pura Vida\n05 - Triggerfinger-I Follow Rivers (Live @ Giel\n06 - Max Graham-Why This Is Goodbye (feat. Jessica Riddle - Album Mix)\n07 - John Mayer-Shadow Days\n08 - Dark Matters-The Quest Of A Dream (feat. Ana Criado)\n09 - Junique-Eine Sekunde (Faris AL-Hassoni Lounge Remix)\n10 - Emily Browning-Asleep\n11 - John O'Callaghan feat. Audrey Gallagher-Big Sky (Acoustic Mix)\n12 - Josh Gabriel Presents Winter Kills-Ichabod (Album Mix Edit)\n13 - Adele-Someone Like You\n14 - Katy Perry-Not Like The Movies\n15 - Bridget, Noochie-Sunshine (Original Version)\n16 - Racoon-Don't Give Up The Fight\n17 - Christophe Willem-Si Mes Larmes Tombent\n18 - Activa-You Are Here (feat. Julie Harrington - Ambient Mix)\n19 - Chris Wonderful-History (Original Mix)\n20 - Zara feat. Jorge Nava-Broken (Chill Out Mix)\n21 - DJ Shah-Over &amp; Over (Acoustic Mix)\n22 - tyDi-Vanilla (feat Tania Zygar - Acoustic Mix)\n23 - Faruk Sabanci-As Faces Fade (Domenico Cascarino &amp; Luca Lombardi Chill Out Remix)\n24 - Etro Anime-Let It Go\n25 - Rossana Casale-Brividi\n26 - Nadia Ali-Fantasy (Original Mix)\n27 - Kirsty Hawkshaw meets Tenishia-Invisible (Kopi Luwak Remix)\n28 - Aly &amp; Fila-Still (feat. Sue McLaren - Original Mix Edit)\n29 - Tenishia &amp; Kirsty Hawkshaw-Falling\n30 - Musette-Redstar (Original Mix)\n31 - Matt Darey, Leah-Hold Your Breath feat. Leah (Original Mix)\n32 - Cantoma-Gambara\n33 - OceanLab-Lonely Girl (Radio Edit)","torrent":{"xt":"urn:btih:e494dab4fa3ad16a2a845387ab648e4c6b6d3860","amp;dn":"Soul+Heaven+Lyrics+%282012%29","amp;tr":["udp%3A%2F%2Ftracker.openbittorrent.com%3A80","udp%3A%2F%2Fopen.demonii.com%3A1337","udp%3A%2F%2Ftracker.coppersurfer.tk%3A6969","udp%3A%2F%2Fexodus.desync.com%3A6969"],"infoHash":"e494dab4fa3ad16a2a845387ab648e4c6b6d3860","infoHashBuffer":{"type":"Buffer","data":[228,148,218,180,250,58,209,106,42,132,83,135,171,100,142,76,107,109,56,96]},"announce":[],"urlList":[]}}