{"title":"Rocco's World Feet Fetish (2013) XXX WEB-DL","uid":8642296,"size":2344380339,"categoryP":"porn","categoryS":"hd___movies","magnet":"?xt=urn:btih:ecde80e7f4e037c2aa3724f7dbe8890c597345af&amp;dn=Rocco%27s+World+Feet+Fetish+%282013%29+XXX+WEB-DL&amp;tr=udp%3A%2F%2Ftracker.openbittorrent.com%3A80&amp;tr=udp%3A%2F%2Fopen.demonii.com%3A1337&amp;tr=udp%3A%2F%2Ftracker.coppersurfer.tk%3A6969&amp;tr=udp%3A%2F%2Fexodus.desync.com%3A6969","seeders":1,"leechers":4,"uploader":"R0thschild","files":4,"time":1372899902,"description":"********************************************\nGallery:  &lt;a href=&quot;\nhttp://publichash.com/index.php?page=torrent-details&amp;id=ecde80e7f4e037c2aa3724f7dbe8890c597345af&quot; rel=&quot;nofollow&quot; target=&quot;_NEW&quot;&gt;\nhttp://publichash.com/index.php?page=torrent-details&amp;id=ecde80e7f4e037c2aa3724f7dbe8890c597345af&lt;/a&gt;\n\n********************************************","torrent":{"xt":"urn:btih:ecde80e7f4e037c2aa3724f7dbe8890c597345af","amp;dn":"Rocco%27s+World+Feet+Fetish+%282013%29+XXX+WEB-DL","amp;tr":["udp%3A%2F%2Ftracker.openbittorrent.com%3A80","udp%3A%2F%2Fopen.demonii.com%3A1337","udp%3A%2F%2Ftracker.coppersurfer.tk%3A6969","udp%3A%2F%2Fexodus.desync.com%3A6969"],"infoHash":"ecde80e7f4e037c2aa3724f7dbe8890c597345af","infoHashBuffer":{"type":"Buffer","data":[236,222,128,231,244,224,55,194,170,55,36,247,219,232,137,12,89,115,69,175]},"announce":[],"urlList":[]}}