{"title":"Skinny Beautiful Chinese Ass Ripped By White Guy.mpg","uid":12547573,"size":162914308,"categoryP":"porn","categoryS":"movie_clips","magnet":"?xt=urn:btih:f465d12976141e515b93206f5035be6019c61b34&amp;dn=Skinny+Beautiful+Chinese+Ass+Ripped+By+White+Guy.mpg&amp;tr=udp%3A%2F%2Ftracker.leechers-paradise.org%3A6969&amp;tr=udp%3A%2F%2Fzer0day.ch%3A1337&amp;tr=udp%3A%2F%2Fopen.demonii.com%3A1337&amp;tr=udp%3A%2F%2Ftracker.coppersurfer.tk%3A6969&amp;tr=udp%3A%2F%2Fexodus.desync.com%3A6969","seeders":1,"leechers":0,"uploader":"Pr0nmaster","files":1,"time":1444498580,"description":"Skinny Beautiful Chinese Ass Ripped By White Guy.mpg\r\n\r\n2015, Anal, Asian, All Sex, Homemade, Amateur, Teen, Hardcore, XXX, Adult\r\n\r\n155.37 MB\r\n\r\nScreens\r\n \nhttp://imgcentral.com/viewer.php?file=09361051511279278422.jpg\r\n \nhttp://imgcentral.com/viewer.php?file=20464119508424739858.jpg","torrent":{"xt":"urn:btih:f465d12976141e515b93206f5035be6019c61b34","amp;dn":"Skinny+Beautiful+Chinese+Ass+Ripped+By+White+Guy.mpg","amp;tr":["udp%3A%2F%2Ftracker.leechers-paradise.org%3A6969","udp%3A%2F%2Fzer0day.ch%3A1337","udp%3A%2F%2Fopen.demonii.com%3A1337","udp%3A%2F%2Ftracker.coppersurfer.tk%3A6969","udp%3A%2F%2Fexodus.desync.com%3A6969"],"infoHash":"f465d12976141e515b93206f5035be6019c61b34","infoHashBuffer":{"type":"Buffer","data":[244,101,209,41,118,20,30,81,91,147,32,111,80,53,190,96,25,198,27,52]},"announce":[],"urlList":[]}}